flake8_leading_blank_lines.py
flake8_leading_blank_lines-1.0.4.dist-info/LICENSE
flake8_leading_blank_lines-1.0.4.dist-info/METADATA
flake8_leading_blank_lines-1.0.4.dist-info/WHEEL
flake8_leading_blank_lines-1.0.4.dist-info/entry_points.txt
flake8_leading_blank_lines-1.0.4.dist-info/top_level.txt
flake8_leading_blank_lines-1.0.4.dist-info/RECORD
