Metadata-Version: 2.1
Name: flake8-leading-blank-lines
Version: 1.0.4
Summary: A flake8 plugin to detect blank lines at the start of a file
Home-page: https://github.com/bmispelon/flake8-leading-blank-lines
Author: Baptiste Mispelon
Author-email: bmispelon@gmail.com
License: MIT
Project-URL: Bug Tracker, https://github.com/bmispelon/flake8-leading-blank-lines/issues
Platform: UNKNOWN
Classifier: Framework :: Flake8
Classifier: Environment :: Console
Classifier: Intended Audience :: Developers
Classifier: License :: OSI Approved :: MIT License
Classifier: Programming Language :: Python
Classifier: Programming Language :: Python :: 3
Classifier: Topic :: Software Development :: Libraries :: Python Modules
Classifier: Topic :: Software Development :: Quality Assurance
License-File: LICENSE
Requires-Dist: flake8 (>3.0.0)
